connectedpapers/__init__.py
connectedpapers/connected_papers_client.py
connectedpapers/consts.py
connectedpapers/graph.py
connectedpapers/py.typed
connectedpapers_py-0.2.5.dist-info/METADATA
connectedpapers_py-0.2.5.dist-info/WHEEL
connectedpapers_py-0.2.5.dist-info/licenses/LICENSE
connectedpapers_py-0.2.5.dist-info/RECORD
