Metadata-Version: 2.4
Name: connectedpapers-py
Version: 0.2.5
Summary: The official python client for the connected papers API.
License: MIT
License-File: LICENSE
Author: ConnectedPapersAdmin
Author-email: admin@connectedpapers.com
Requires-Python: >=3.8.1
Classifier: License :: OSI Approved :: MIT License
Classifier: Programming Language :: Python :: 3
Classifier: Programming Language :: Python :: 3.9
Classifier: Programming Language :: Python :: 3.10
Classifier: Programming Language :: Python :: 3.11
Classifier: Programming Language :: Python :: 3.12
Classifier: Programming Language :: Python :: 3.13
Classifier: Programming Language :: Python :: 3.14
Requires-Dist: aiohttp (>=2.0.0)
Requires-Dist: dacite (>=1.8.1,<2.0.0)
Requires-Dist: nest-asyncio (>=1.5.7,<2.0.0)
Requires-Dist: requests (>=2.0.0)
Project-URL: Repository, https://github.com/ConnectedPapers/connectedpapers-py/
